pyroboplan/__init__.py
pyroboplan/core/__init__.py
pyroboplan/core/planning_context.py
pyroboplan/core/utils.py
pyroboplan/ik/__init__.py
pyroboplan/ik/differential_ik.py
pyroboplan/ik/nullspace_components.py
pyroboplan/models/__init__.py
pyroboplan/models/marble.py
pyroboplan/models/panda.py
pyroboplan/models/two_dof.py
pyroboplan/models/ur10.py
pyroboplan/models/ur5.py
pyroboplan/models/utils.py
pyroboplan/models/example_point_cloud/example_point_cloud.ply
pyroboplan/models/marble_description/marble.urdf
pyroboplan/models/panda_description/LICENSE
pyroboplan/models/panda_description/README.md
pyroboplan/models/panda_description/meshes/collision/finger.stl
pyroboplan/models/panda_description/meshes/collision/hand.stl
pyroboplan/models/panda_description/meshes/collision/link0.stl
pyroboplan/models/panda_description/meshes/collision/link1.stl
pyroboplan/models/panda_description/meshes/collision/link2.stl
pyroboplan/models/panda_description/meshes/collision/link3.stl
pyroboplan/models/panda_description/meshes/collision/link4.stl
pyroboplan/models/panda_description/meshes/collision/link5.stl
pyroboplan/models/panda_description/meshes/collision/link6.stl
pyroboplan/models/panda_description/meshes/collision/link7.stl
pyroboplan/models/panda_description/meshes/visual/finger.dae
pyroboplan/models/panda_description/meshes/visual/hand.dae
pyroboplan/models/panda_description/meshes/visual/link0.dae
pyroboplan/models/panda_description/meshes/visual/link1.dae
pyroboplan/models/panda_description/meshes/visual/link2.dae
pyroboplan/models/panda_description/meshes/visual/link3.dae
pyroboplan/models/panda_description/meshes/visual/link4.dae
pyroboplan/models/panda_description/meshes/visual/link5.dae
pyroboplan/models/panda_description/meshes/visual/link6.dae
pyroboplan/models/panda_description/meshes/visual/link7.dae
pyroboplan/models/panda_description/srdf/panda.srdf
pyroboplan/models/panda_description/urdf/panda.urdf
pyroboplan/models/panda_description/urdf/panda_spheres.urdf
pyroboplan-1.3.0.dist-info/METADATA
pyroboplan-1.3.0.dist-info/WHEEL
pyroboplan-1.3.0.dist-info/licenses/LICENSE
pyroboplan-1.3.0.dist-info/RECORD
