Metadata-Version: 2.4
Name: pyroboplan
Version: 1.3.0
Summary: Educational Python library for manipulator motion planning.
Author-email: Sebastian Castro <sebas.a.castro@gmail.com>
Maintainer-email: Sebastian Castro <sebas.a.castro@gmail.com>
License: MIT License
License-File: LICENSE
Keywords: education,manipulators,motion planning
Requires-Python: >=3.10
Requires-Dist: drake==1.43.0
Requires-Dist: matplotlib==3.10.5
Requires-Dist: meshcat==0.3.2
Requires-Dist: pin==3.7.0
Requires-Dist: plyfile==1.1.2
Requires-Dist: scipy==1.15.3
Requires-Dist: toppra==0.6.3
